didatictests/__init__.py
didatictests/didatictests.py
didatictests/example.py
didatictests/bin/__init__.py
didatictests/bin/my_example.py
didatictests-0.0.9.dist-info/LICENSE
didatictests-0.0.9.dist-info/METADATA
didatictests-0.0.9.dist-info/WHEEL
didatictests-0.0.9.dist-info/entry_points.txt
didatictests-0.0.9.dist-info/top_level.txt
didatictests-0.0.9.dist-info/RECORD
